pysparkhdfshelper/__init__.py
pysparkhdfshelper/pysparkhdfshelper.py
pysparkhdfshelper-0.0.5.dist-info/METADATA
pysparkhdfshelper-0.0.5.dist-info/WHEEL
pysparkhdfshelper-0.0.5.dist-info/top_level.txt
pysparkhdfshelper-0.0.5.dist-info/RECORD
