Metadata-Version: 2.1
Name: pysparkhdfshelper
Version: 0.0.5
Requires-Dist: logclshelper
Requires-Dist: pysparkhelper
